{
  "title":"How to Make Lime Syrup",
  "url":"https://www.wikihow.com/Make-Lime-Syrup",
  "category_hierarchy":[
    "Food and Entertaining",
    "Recipes",
    "Jams Preserves and Condiments",
    "Syrups"
  ],
  "steps":[
    {
      "headline":"Pour the juice, sugar and water into a small, heavy-based saucepan.",
      "description":""
    },
    {
      "headline":"Stir over medium heat.",
      "description":"Do not bring to the boil just yet. Continue stirring until the sugar has completely dissolved."
    },
    {
      "headline":"Bring to the boil.",
      "description":"Reduce to a simmer and allow to continue cooking for 1 minute."
    },
    {
      "headline":"Remove the syrup from the heat.",
      "description":""
    },
    {
      "headline":"Allow to cool a little before serving as a warm sauce.",
      "description":"Allow to cool completely before serving as a cold syrup."
    }
  ],
  "text":" Pour the juice, sugar and water into a small, heavy-based saucepan.  Stir over medium heat. Do not bring to the boil just yet. Continue stirring until the sugar has completely dissolved. Bring to the boil. Reduce to a simmer and allow to continue cooking for 1 minute. Remove the syrup from the heat.  Allow to cool a little before serving as a warm sauce. Allow to cool completely before serving as a cold syrup.",
  "tyn_model":[
    "sugar",
    "water",
    "small, heavy-based saucepan",
    "cold syrup"
  ],
  "tyn_section":[

  ]
}