{
  "title":"How to Make Carrot Tortillas",
  "url":"https://www.wikihow.com/Make-Carrot-Tortillas",
  "category_hierarchy":[
    "Food and Entertaining",
    "Recipes",
    "Baking",
    "Breads",
    "Flat Breads"
  ],
  "steps":[
    {
      "headline":"Mix flour, salt, and baking powder together.",
      "description":""
    },
    {
      "headline":"Add oil and mix until you can ball the flour up.",
      "description":"It should be like playdough but it will crumble very easily."
    },
    {
      "headline":"Heat carrot puree just until warm.",
      "description":""
    },
    {
      "headline":"Add carrot puree to the flour mixture until it doesn't stick to the side of the mixing bowl anymore.",
      "description":"Add more small amounts of flour and/ or warm water if needed to get to that consistency. You want your dough to be sticky enough to be able to handle it but not sticky enough that when you start to roll it out you need flour."
    },
    {
      "headline":"Let the masa sit in a bowl covered with a towel for about 15 minutes",
      "description":""
    },
    {
      "headline":"Separate masa into 2 inch (5.1 cm) balls (bigger or smaller depending on how big you want the tortillas).",
      "description":""
    },
    {
      "headline":"Roll the masa out until it is \u20448 inch (0.3 cm) thick.",
      "description":""
    },
    {
      "headline":"Cook the tortilla on one side until it starts to bubble.",
      "description":"Then flip it and cook on the other side until done."
    },
    {
      "headline":"Place your tortillas on a covered plate or in a tortilla warmer.",
      "description":""
    }
  ],
  "text":" Mix flour, salt, and baking powder together.  Add oil and mix until you can ball the flour up. It should be like playdough but it will crumble very easily. Heat carrot puree just until warm.  Add carrot puree to the flour mixture until it doesn't stick to the side of the mixing bowl anymore. Add more small amounts of flour and/ or warm water if needed to get to that consistency. You want your dough to be sticky enough to be able to handle it but not sticky enough that when you start to roll it out you need flour. Let the masa sit in a bowl covered with a towel for about 15 minutes  Separate masa into 2 inch (5.1 cm) balls (bigger or smaller depending on how big you want the tortillas).  Roll the masa out until it is \u20448 inch (0.3 cm) thick.  Cook the tortilla on one side until it starts to bubble. Then flip it and cook on the other side until done. Place your tortillas on a covered plate or in a tortilla warmer. ",
  "tyn_model":[
    "flour",
    "carrot puree",
    "salt",
    "baking powder",
    "oil",
    "mixing bowl",
    "water",
    "bowl",
    "plate",
    "tortilla warmer"
  ],
  "tyn_section":[

  ]
}