{
  "title":"How to Make Rum Punch",
  "url":"https://www.wikihow.com/Make-Rum-Punch",
  "category_hierarchy":[
    "Food and Entertaining",
    "Drinks",
    "Alcoholic Drinks",
    "Spirits and Liqueurs",
    "Cocktails",
    "Rum Based Cocktails"
  ],
  "methods":[
    {
      "name":"Simple rum punch",
      "steps":[
        {
          "headline":"Mix Kilo Kai or other rum, lemon juice and grenadine in shaker with ice.",
          "description":""
        },
        {
          "headline":"Pour into glass and top with club soda.",
          "description":""
        },
        {
          "headline":"Garnish with orange and lemon slices.",
          "description":""
        }
      ]
    },
    {
      "name":"Mango rum punch",
      "steps":[
        {
          "headline":"Pre-chill the glasses.",
          "description":"Place them in the refrigerator at least half an hour before making the punch."
        },
        {
          "headline":"Place the mango pur\u00e9e or frozen mango into the blender.",
          "description":""
        },
        {
          "headline":"Add the lemon juice, cardamom spice and rum.",
          "description":""
        },
        {
          "headline":"Add 4 to 6 ice cubes.",
          "description":""
        },
        {
          "headline":"Blend everything together.",
          "description":"Keep blending until the mixture turns smooth."
        },
        {
          "headline":"Strain into the chilled glasses.",
          "description":""
        },
        {
          "headline":"Add ice if wished.",
          "description":"This is optional if you feel it's already cold enough."
        },
        {
          "headline":"Top with a garnish.",
          "description":"Cardamom seeds are nice, or a mint leaf or two."
        }
      ]
    }
  ],
  "text":" Simple rum punch Mix Kilo Kai or other rum, lemon juice and grenadine in shaker with ice.  Pour into glass and top with club soda.  Garnish with orange and lemon slices.  Mango rum punch Pre-chill the glasses. Place them in the refrigerator at least half an hour before making the punch. Place the mango pur\u00e9e or frozen mango into the blender.  Add the lemon juice, cardamom spice and rum.  Add 4 to 6 ice cubes.  Blend everything together. Keep blending until the mixture turns smooth. Strain into the chilled glasses.  Add ice if wished. This is optional if you feel it's already cold enough. Top with a garnish. Cardamom seeds are nice, or a mint leaf or two.",
  "tyn_model":[
    "rum",
    "ice",
    "glasses",
    "simple rum",
    "lemon juice",
    "grenadine",
    "shaker",
    "club soda",
    "mango rum",
    "refrigerator",
    "mango pur\u00e9e",
    "mango",
    "blender",
    "lemon",
    "cardamom spice",
    "ice cubes",
    "cardamom",
    "mint leaf"
  ],
  "tyn_section":[

  ]
}