{
    "title": "How to Use Shea Butter",
    "url": "https://www.wikihow.com/Use-Shea-Butter",
    "category_hierarchy": [
        "Personal Care and Style",
        "Skin Care",
        "Skin Care Products"
    ],
    "methods": [
        {
            "name": "Using Shea Butter on Skin and Hair",
            "steps": [
                {
                    "headline": "Use shea butter as a moisturizer.",
                    "description": "Simply scoop some shea butter up from the jar and rub it over your skin, focusing on the areas that are dry (such as the hands, elbows, and feet)."
                },
                {
                    "headline": "Get rid of stretch marks or cellulite using shea butter.",
                    "description": "Since it is very high in Vitamins A, E & F, shea butter aids in cell regeneration and circulation. Apply a small amount of shea butter onto the affected areas and massage it in, much like you would with any other lotion\nWhen treating stretch marks, use the shea butter twice a day."
                },
                {
                    "headline": "Apply shea butter on your face before putting on makeup.",
                    "description": "It makes a great moisturizer, and helps replenish the skin. You can also use it under your eyes if you have under eye bags or shadows."
                },
                {
                    "headline": "Use shea butter in homemade bath and beauty products.",
                    "description": "Because of its moisturizing qualities and high-vitamin content, shea butter is a great ingredient for many homemade bath and beauty products, including:\nBody butters, and melts\n\nBody scrubs\nSoaps and lotions\nLip balms\nShaving cream"
                },
                {
                    "headline": "Soften and tame frizz using a shea butter hair mask.",
                    "description": "Warm a few tablespoons of shea butter over the stove or in the microwave. Massage it into your hair, focusing on the dry ends first and moving gradually upwards towards the scalp. Tuck your hair under a shower cap and wait 30 minutes. Wash and rinse the hair mask out, then follow with your usual shampoo and conditioner."
                }
            ]
        },
        {
            "name": "Using Shea Butter to Make Lip Balm",
            "steps": [
                {
                    "headline": "Gather your ingredients.",
                    "description": "To make some lip balm, you will need a double-boiler, some small containers, and the following ingredients:\n2 tablespoons beeswax\n2 tablespoons shea butter\n2 tablespoons coconut oil\n6 \u2013 12 drops essential oil (optional)"
                },
                {
                    "headline": "Set up your double-boiler.",
                    "description": "If you do not have one, fill a large pot with a few inches of water, then place a large bowl on top of the pot. The bottom of the bowl should not be touching the water."
                },
                {
                    "headline": "Turn the stove on and bring the water to a simmer.",
                    "description": "If you cannot see the water, then just watch for the steam."
                },
                {
                    "headline": "Add the beeswax, shea butter, and coconut oil into the double-boiler, and melt them.",
                    "description": "Be sure to stir your ingredients often so that they melt evenly and become mixed."
                },
                {
                    "headline": "Consider adding some essential oil.",
                    "description": "You can leave your lip balm plain, or you can add some flavor to it with 6 to 12 drops of essential oil. Oils that would work well with shea butter include vanilla, lavender, and rose. After you have added the oils, give the mixture another stir to blend everything together."
                },
                {
                    "headline": "Transfer the lip balm to your containers.",
                    "description": "Work quickly before the mixture hardens. You can use anything to store your lip balm, so long as it has a tight-fitting lid. If you are having difficulties pouring the mixture in, then you can use a spoon or eyedropper to transfer the mixture from the pot to the containers."
                }
            ]
        },
        {
            "name": "Using Shea Butter to Make Body Melts",
            "steps": [
                {
                    "headline": "Gather your ingredients.",
                    "description": "To make some luxurious shea butter body melts, you will need equal parts of shea, grated beeswax, and food-grade oil (such as olive oil or coconut oil). You will also need something to use as molds, such as a silicone ice cube tray or candy molds. If you want fragranced body melts, you can add a few drops of essential oil, such as rose, lavender, or vanilla."
                },
                {
                    "headline": "Set up a double-boiler.",
                    "description": "If you do not have one, you can make your own by filling a large pot with 2 to 3 inches (5 to 7.5 centimeters) of water, and placing a large bowl on top. The bowl should fit snugly and not touch the water."
                },
                {
                    "headline": "Bring the water to a simmer.",
                    "description": "Set the heat on your stove to \"medium\" and wait for the water to begin steaming."
                },
                {
                    "headline": "Add the beeswax and wait for it to melt.",
                    "description": "Be sure to stir if often so that it melts evenly and does not scorch."
                },
                {
                    "headline": "Add the rest of the ingredients.",
                    "description": "Keep stirring until everything is melted and spread evenly throughout."
                },
                {
                    "headline": "Remove the mixture from heat and pour into your molds.",
                    "description": "Work quickly so that the mixture does not harden while you are pouring it."
                },
                {
                    "headline": "Wait for the body melts to set, then use.",
                    "description": "You can use them by massaging them over your skin. The wax and shea butter will melt, leaving a thin film on your skin. The film will get absorbed into your skin, leaving it feeling soft and smooth."
                }
            ]
        },
        {
            "name": "Using Shea Butter to Make Shaving Cream",
            "steps": [
                {
                    "headline": "Gather your ingredients.",
                    "description": "You can make some luxurious and moisturizing shaving cream using shea butter and a few other ingredients. Here is what you will need:\n1/3 cup coconut oil\n1/3 cup shea butter\n\u00bc cup olive oil"
                },
                {
                    "headline": "Melt the coconut oil and shea butter in a small pot.",
                    "description": "Put the pot on the stove, and set the heat to \"low.\" Drop in your oil and butter and wait for both to melt. Be sure to stir every so often so that they melt evenly. Because of their low melting points, this should not take long."
                },
                {
                    "headline": "Pour the melted butter and oil into a bowl and add the olive oil.",
                    "description": "Once the coconut oil and shea butter have melted, lift the pot off the stove and transfer everything into a heat-safe bowl. Add in the olive oil and stir to blend everything together. The liquid will look translucent."
                },
                {
                    "headline": "Put the bowl into the fridge and let it cool.",
                    "description": "As the oils and butters harden, they will turn an opaque yellow color. Consider labeling this bowl so that someone does not mistake your shaving cream for butter and eat it."
                },
                {
                    "headline": "Whip the hardened oils and butters until they become light and fluffy.",
                    "description": "You can do this by using a hand mixer, or a food processor with a whisk attachment. This should take about three minutes."
                },
                {
                    "headline": "Transfer the shaving cream to a seal-able container and store it properly.",
                    "description": "Because of the low-melting points of coconut oil and shea butter, you will need to store your shaving cream in a cool, dry place."
                }
            ]
        },
        {
            "name": "Using Shea Butter for Cooking",
            "steps": [
                {
                    "headline": "Consider using unrefined shea butter in cooking.",
                    "description": "The difference between unrefined and refined shea butter is that unrefined shea butter is pure, full of nutrients, and has a slight, nutty flavor; refined shea butter, on the other hand, lacks some of its natural nutrients and is also mostly odorless and flavorless."
                },
                {
                    "headline": "Replace butter with shea butter when cooking.",
                    "description": "If your recipe calls for regular butter, but you don't happen to have any at home, you can use shea butter as a substitute."
                },
                {
                    "headline": "Use shea butter when frying.",
                    "description": "Instead of using cooking oil or butter, consider using some shea butter instead. It is solid at room temperature, but it has a low melting point and will soften quickly in the frying pan. It will also lend your food a nuttier flavor."
                },
                {
                    "headline": "Use shea butter when making chocolate.",
                    "description": "Instead of using butter, you can use shea butter instead. It will give the chocolate a slight, nut-like flavor."
                }
            ]
        }
    ],
    "tyn": [
        "Shea butter."
    ],
    "text": " Using Shea Butter on Skin and Hair Use shea butter as a moisturizer. Simply scoop some shea butter up from the jar and rub it over your skin, focusing on the areas that are dry (such as the hands, elbows, and feet). Get rid of stretch marks or cellulite using shea butter. Since it is very high in Vitamins A, E & F, shea butter aids in cell regeneration and circulation. Apply a small amount of shea butter onto the affected areas and massage it in, much like you would with any other lotion\nWhen treating stretch marks, use the shea butter twice a day. Apply shea butter on your face before putting on makeup. It makes a great moisturizer, and helps replenish the skin. You can also use it under your eyes if you have under eye bags or shadows. Use shea butter in homemade bath and beauty products. Because of its moisturizing qualities and high-vitamin content, shea butter is a great ingredient for many homemade bath and beauty products, including:\nBody butters, and melts\n\nBody scrubs\nSoaps and lotions\nLip balms\nShaving cream Soften and tame frizz using a shea butter hair mask. Warm a few tablespoons of shea butter over the stove or in the microwave. Massage it into your hair, focusing on the dry ends first and moving gradually upwards towards the scalp. Tuck your hair under a shower cap and wait 30 minutes. Wash and rinse the hair mask out, then follow with your usual shampoo and conditioner. Using Shea Butter to Make Lip Balm Gather your ingredients. To make some lip balm, you will need a double-boiler, some small containers, and the following ingredients:\n2 tablespoons beeswax\n2 tablespoons shea butter\n2 tablespoons coconut oil\n6 \u2013 12 drops essential oil (optional) Set up your double-boiler. If you do not have one, fill a large pot with a few inches of water, then place a large bowl on top of the pot. The bottom of the bowl should not be touching the water. Turn the stove on and bring the water to a simmer. If you cannot see the water, then just watch for the steam. Add the beeswax, shea butter, and coconut oil into the double-boiler, and melt them. Be sure to stir your ingredients often so that they melt evenly and become mixed. Consider adding some essential oil. You can leave your lip balm plain, or you can add some flavor to it with 6 to 12 drops of essential oil. Oils that would work well with shea butter include vanilla, lavender, and rose. After you have added the oils, give the mixture another stir to blend everything together. Transfer the lip balm to your containers. Work quickly before the mixture hardens. You can use anything to store your lip balm, so long as it has a tight-fitting lid. If you are having difficulties pouring the mixture in, then you can use a spoon or eyedropper to transfer the mixture from the pot to the containers. Using Shea Butter to Make Body Melts Gather your ingredients. To make some luxurious shea butter body melts, you will need equal parts of shea, grated beeswax, and food-grade oil (such as olive oil or coconut oil). You will also need something to use as molds, such as a silicone ice cube tray or candy molds. If you want fragranced body melts, you can add a few drops of essential oil, such as rose, lavender, or vanilla. Set up a double-boiler. If you do not have one, you can make your own by filling a large pot with 2 to 3 inches (5 to 7.5 centimeters) of water, and placing a large bowl on top. The bowl should fit snugly and not touch the water. Bring the water to a simmer. Set the heat on your stove to \"medium\" and wait for the water to begin steaming. Add the beeswax and wait for it to melt. Be sure to stir if often so that it melts evenly and does not scorch. Add the rest of the ingredients. Keep stirring until everything is melted and spread evenly throughout. Remove the mixture from heat and pour into your molds. Work quickly so that the mixture does not harden while you are pouring it. Wait for the body melts to set, then use. You can use them by massaging them over your skin. The wax and shea butter will melt, leaving a thin film on your skin. The film will get absorbed into your skin, leaving it feeling soft and smooth. Using Shea Butter to Make Shaving Cream Gather your ingredients. You can make some luxurious and moisturizing shaving cream using shea butter and a few other ingredients. Here is what you will need:\n1/3 cup coconut oil\n1/3 cup shea butter\n\u00bc cup olive oil Melt the coconut oil and shea butter in a small pot. Put the pot on the stove, and set the heat to \"low.\" Drop in your oil and butter and wait for both to melt. Be sure to stir every so often so that they melt evenly. Because of their low melting points, this should not take long. Pour the melted butter and oil into a bowl and add the olive oil. Once the coconut oil and shea butter have melted, lift the pot off the stove and transfer everything into a heat-safe bowl. Add in the olive oil and stir to blend everything together. The liquid will look translucent. Put the bowl into the fridge and let it cool. As the oils and butters harden, they will turn an opaque yellow color. Consider labeling this bowl so that someone does not mistake your shaving cream for butter and eat it. Whip the hardened oils and butters until they become light and fluffy. You can do this by using a hand mixer, or a food processor with a whisk attachment. This should take about three minutes. Transfer the shaving cream to a seal-able container and store it properly. Because of the low-melting points of coconut oil and shea butter, you will need to store your shaving cream in a cool, dry place. Using Shea Butter for Cooking Consider using unrefined shea butter in cooking. The difference between unrefined and refined shea butter is that unrefined shea butter is pure, full of nutrients, and has a slight, nutty flavor; refined shea butter, on the other hand, lacks some of its natural nutrients and is also mostly odorless and flavorless. Replace butter with shea butter when cooking. If your recipe calls for regular butter, but you don't happen to have any at home, you can use shea butter as a substitute. Use shea butter when frying. Instead of using cooking oil or butter, consider using some shea butter instead. It is solid at room temperature, but it has a low melting point and will soften quickly in the frying pan. It will also lend your food a nuttier flavor. Use shea butter when making chocolate. Instead of using butter, you can use shea butter instead. It will give the chocolate a slight, nut-like flavor.",
    "sentences": [
        " Using Shea Butter on Skin and Hair Use shea butter as a moisturizer.",
        "Simply scoop some shea butter up from the jar and rub it over your skin, focusing on the areas that are dry (such as the hands, elbows, and feet).",
        "Get rid of stretch marks or cellulite using shea butter.",
        "Since it is very high in Vitamins A, E & F, shea butter aids in cell regeneration and circulation.",
        "Apply a small amount of shea butter onto the affected areas and massage it in, much like you would with any other lotion\nWhen treating stretch marks, use the shea butter twice a day.",
        "Apply shea butter on your face before putting on makeup.",
        "It makes a great moisturizer, and helps replenish the skin.",
        "You can also use it under your eyes if you have under eye bags or shadows.",
        "Use shea butter in homemade bath and beauty products.",
        "Because of its moisturizing qualities and high-vitamin content, shea butter is a great ingredient for many homemade bath and beauty products, including:\nBody butters, and melts\n\nBody scrubs\nSoaps and lotions\nLip balms\nShaving cream Soften and tame frizz using a shea butter hair mask.",
        "Warm a few tablespoons of shea butter over the stove or in the microwave.",
        "Massage it into your hair, focusing on the dry ends first and moving gradually upwards towards the scalp.",
        "Tuck your hair under a shower cap and wait 30 minutes.",
        "Wash and rinse the hair mask out, then follow with your usual shampoo and conditioner.",
        "Using Shea Butter to Make Lip Balm Gather your ingredients.",
        "To make some lip balm, you will need a double-boiler, some small containers, and the following ingredients:\n2 tablespoons beeswax\n2 tablespoons shea butter\n2 tablespoons coconut oil\n6 \u2013 12 drops essential oil (optional) Set up your double-boiler.",
        "If you do not have one, fill a large pot with a few inches of water, then place a large bowl on top of the pot.",
        "The bottom of the bowl should not be touching the water.",
        "Turn the stove on and bring the water to a simmer.",
        "If you cannot see the water, then just watch for the steam.",
        "Add the beeswax, shea butter, and coconut oil into the double-boiler, and melt them.",
        "Be sure to stir your ingredients often so that they melt evenly and become mixed.",
        "Consider adding some essential oil.",
        "You can leave your lip balm plain, or you can add some flavor to it with 6 to 12 drops of essential oil.",
        "Oils that would work well with shea butter include vanilla, lavender, and rose.",
        "After you have added the oils, give the mixture another stir to blend everything together.",
        "Transfer the lip balm to your containers.",
        "Work quickly before the mixture hardens.",
        "You can use anything to store your lip balm, so long as it has a tight-fitting lid.",
        "If you are having difficulties pouring the mixture in, then you can use a spoon or eyedropper to transfer the mixture from the pot to the containers.",
        "Using Shea Butter to Make Body Melts Gather your ingredients.",
        "To make some luxurious shea butter body melts, you will need equal parts of shea, grated beeswax, and food-grade oil (such as olive oil or coconut oil).",
        "You will also need something to use as molds, such as a silicone ice cube tray or candy molds.",
        "If you want fragranced body melts, you can add a few drops of essential oil, such as rose, lavender, or vanilla.",
        "Set up a double-boiler.",
        "If you do not have one, you can make your own by filling a large pot with 2 to 3 inches (5 to 7.5 centimeters) of water, and placing a large bowl on top.",
        "The bowl should fit snugly and not touch the water.",
        "Bring the water to a simmer.",
        "Set the heat on your stove to \"medium\" and wait for the water to begin steaming.",
        "Add the beeswax and wait for it to melt.",
        "Be sure to stir if often so that it melts evenly and does not scorch.",
        "Add the rest of the ingredients.",
        "Keep stirring until everything is melted and spread evenly throughout.",
        "Remove the mixture from heat and pour into your molds.",
        "Work quickly so that the mixture does not harden while you are pouring it.",
        "Wait for the body melts to set, then use.",
        "You can use them by massaging them over your skin.",
        "The wax and shea butter will melt, leaving a thin film on your skin.",
        "The film will get absorbed into your skin, leaving it feeling soft and smooth.",
        "Using Shea Butter to Make Shaving Cream Gather your ingredients.",
        "You can make some luxurious and moisturizing shaving cream using shea butter and a few other ingredients.",
        "Here is what you will need:\n1/3 cup coconut oil\n1/3 cup shea butter\n\u00bc cup olive oil Melt the coconut oil and shea butter in a small pot.",
        "Put the pot on the stove, and set the heat to \"low.\"",
        "Drop in your oil and butter and wait for both to melt.",
        "Be sure to stir every so often so that they melt evenly.",
        "Because of their low melting points, this should not take long.",
        "Pour the melted butter and oil into a bowl and add the olive oil.",
        "Once the coconut oil and shea butter have melted, lift the pot off the stove and transfer everything into a heat-safe bowl.",
        "Add in the olive oil and stir to blend everything together.",
        "The liquid will look translucent.",
        "Put the bowl into the fridge and let it cool.",
        "As the oils and butters harden, they will turn an opaque yellow color.",
        "Consider labeling this bowl so that someone does not mistake your shaving cream for butter and eat it.",
        "Whip the hardened oils and butters until they become light and fluffy.",
        "You can do this by using a hand mixer, or a food processor with a whisk attachment.",
        "This should take about three minutes.",
        "Transfer the shaving cream to a seal-able container and store it properly.",
        "Because of the low-melting points of coconut oil and shea butter, you will need to store your shaving cream in a cool, dry place.",
        "Using Shea Butter for Cooking Consider using unrefined shea butter in cooking.",
        "The difference between unrefined and refined shea butter is that unrefined shea butter is pure, full of nutrients, and has a slight, nutty flavor; refined shea butter, on the other hand, lacks some of its natural nutrients and is also mostly odorless and flavorless.",
        "Replace butter with shea butter when cooking.",
        "If your recipe calls for regular butter, but you don't happen to have any at home, you can use shea butter as a substitute.",
        "Use shea butter when frying.",
        "Instead of using cooking oil or butter, consider using some shea butter instead.",
        "It is solid at room temperature, but it has a low melting point and will soften quickly in the frying pan.",
        "It will also lend your food a nuttier flavor.",
        "Use shea butter when making chocolate.",
        "Instead of using butter, you can use shea butter instead.",
        "It will give the chocolate a slight, nut-like flavor."
    ]
}