{
    "title": "How to Make Soapy Water Garden Spray",
    "url": "https://www.wikihow.com/Make-Soapy-Water-Garden-Spray",
    "category_hierarchy": [
        "Home and Garden",
        "Gardening",
        "Garden Pests and Weeds",
        "Garden Sprays"
    ],
    "steps": [
        {
            "headline": "Purchase soap powder.",
            "description": "Check that it is pure and does not contain chemical additives."
        },
        {
            "headline": "Mix the soap powder and water together.",
            "description": ""
        },
        {
            "headline": "Transfer the mixture to a spray bottle.",
            "description": ""
        },
        {
            "headline": "Use immediately.",
            "description": "There is no point storing this spray mixture  - discard unwanted mixture down the drain."
        }
    ],
    "tyn": [
        "Mixing container",
        "Spray bottle"
    ],
    "text": " Purchase soap powder. Check that it is pure and does not contain chemical additives. Mix the soap powder and water together.  Transfer the mixture to a spray bottle.  Use immediately. There is no point storing this spray mixture  - discard unwanted mixture down the drain.",
    "sentences": [
        " Purchase soap powder.",
        "Check that it is pure and does not contain chemical additives.",
        "Mix the soap powder and water together.",
        "Transfer the mixture to a spray bottle.",
        "Use immediately.",
        "There is no point storing this spray mixture  - discard unwanted mixture down the drain."
    ]
}